LICENSE
README.md
token_throttler/__init__.py
token_throttler/exception.py
token_throttler/ext/__init__.py
token_throttler/ext/fastapi.py
token_throttler/py.typed
token_throttler/storage/__init__.py
token_throttler/storage/bucket_storage.py
token_throttler/storage/bucket_storage_async.py
token_throttler/storage/redis/__init__.py
token_throttler/storage/redis/redis_storage.py
token_throttler/storage/redis/redis_storage_async.py
token_throttler/storage/runtime_storage.py
token_throttler/throttler_config.py
token_throttler/token_bucket.py
token_throttler/token_throttler.py
token_throttler/token_throttler_async.py
token_throttler/validate.py
token_throttler-1.5.1.dist-info/LICENSE
token_throttler-1.5.1.dist-info/METADATA
token_throttler-1.5.1.dist-info/WHEEL
token_throttler-1.5.1.dist-info/RECORD
