Metadata-Version: 2.1
Name: token-throttler
Version: 1.5.1
Summary: Token throttler is an extendable rate-limiting library somewhat based on a token bucket algorithm
Home-page: https://gitlab.com/vojko.pribudic/token-throttler
License: MIT
Author: Vojko Pribudić
Author-email: dmanthing@gmail.com
Maintainer: Vojko Pribudić
Maintainer-email: dmanthing@gmail.com
Requires-Python: >=3.8,<4.0
Classifier: Development Status :: 5 - Production/Stable
Classifier: Environment :: Web Environment
Classifier: Intended Audience :: Developers
Classifier: License :: OSI Approved :: MIT License
Classifier: Natural Language :: English
Classifier: Operating System :: OS Independent
Classifier: Programming Language :: Python
Classifier: Programming Language :: Python :: 3
Classifier: Programming Language :: Python :: 3.8
Classifier: Programming Language :: Python :: 3.9
Classifier: Programming Language :: Python :: 3.10
Classifier: Programming Language :: Python :: 3.11
Classifier: Programming Language :: Python :: 3.12
Classifier: Programming Language :: Python :: 3 :: Only
Classifier: Topic :: Software Development :: Libraries
Provides-Extra: fastapi
Provides-Extra: redis
Requires-Dist: fastapi (>=0.102.0) ; extra == "fastapi"
Requires-Dist: redis (>=4.4) ; extra == "redis"
Project-URL: Changelog, https://gitlab.com/vojko.pribudic/token-throttler/-/releases
Project-URL: Repository, https://gitlab.com/vojko.pribudic/token-throttler
Project-URL: Tracker, https://gitlab.com/vojko.pribudic/token-throttler/-/issues
